cosmix/__init__.py
cosmix/_version.py
cosmix/fixed_volume_mix.py
cosmix/format.py
cosmix/gsheets_integration.py
cosmix_wetlab-0.0.30.dist-info/LICENSE
cosmix_wetlab-0.0.30.dist-info/METADATA
cosmix_wetlab-0.0.30.dist-info/WHEEL
cosmix_wetlab-0.0.30.dist-info/top_level.txt
cosmix_wetlab-0.0.30.dist-info/RECORD
