Metadata-Version: 2.1
Name: cosmix-wetlab
Version: 0.0.30
Summary: Utility to create wet-lab mixes and integrations with third-parties such as Google Sheets
Home-page: https://github.com/tcosmo/cosmix
Author: Tristan Stérin
Author-email: tristan.sterin@mu.ie
License: UNKNOWN
Platform: UNKNOWN
Classifier: Programming Language :: Python :: 3
Classifier: License :: OSI Approved :: MIT License
Classifier: Operating System :: OS Independent
License-File: LICENSE
Requires-Dist: Pint ==0.18
Requires-Dist: cachetools ==4.2.4
Requires-Dist: certifi ==2021.10.8
Requires-Dist: charset-normalizer ==2.0.7
Requires-Dist: google-auth-oauthlib ==0.4.6
Requires-Dist: google-auth ==2.3.3
Requires-Dist: gspread ==4.0.1
Requires-Dist: idna ==3.3
Requires-Dist: numpy ==1.26.0
Requires-Dist: oauthlib ==3.1.1
Requires-Dist: packaging ==21.3
Requires-Dist: pyasn1-modules ==0.2.8
Requires-Dist: pyasn1 ==0.4.8
Requires-Dist: pyparsing ==3.0.6
Requires-Dist: requests-oauthlib ==1.3.0
Requires-Dist: requests ==2.26.0
Requires-Dist: rsa ==4.7.2
Requires-Dist: six ==1.16.0
Requires-Dist: tabulate ==0.8.9
Requires-Dist: urllib3 ==1.26.7
